pytest_win32consoletitle/__init__.py
pytest_win32consoletitle/plugin.py
pytest_win32consoletitle-0.1.2.dist-info/LICENSE
pytest_win32consoletitle-0.1.2.dist-info/METADATA
pytest_win32consoletitle-0.1.2.dist-info/WHEEL
pytest_win32consoletitle-0.1.2.dist-info/entry_points.txt
pytest_win32consoletitle-0.1.2.dist-info/top_level.txt
pytest_win32consoletitle-0.1.2.dist-info/RECORD
